wkstock/__init__.py
wkstock/data/stock-info-20201123.txt
wkstock/utils/__init__.py
wkstock/utils/apis.py
wkstock/utils/china_stock_market.py
wkstock/utils/get_stock_info.py
wkstock-0.0.0.4.dist-info/LICENSE
wkstock-0.0.0.4.dist-info/METADATA
wkstock-0.0.0.4.dist-info/WHEEL
wkstock-0.0.0.4.dist-info/entry_points.txt
wkstock-0.0.0.4.dist-info/top_level.txt
wkstock-0.0.0.4.dist-info/RECORD
