Metadata-Version: 2.1
Name: wkstock
Version: 0.0.0.4
Summary: python utils for stock research.
Home-page: http://github.com/Peiiii/wkstock
Author: WangPei
Author-email: 1535376447@qq.com
License: UNKNOWN
Platform: UNKNOWN
Classifier: Programming Language :: Python :: 3
Classifier: License :: OSI Approved :: MIT License
Classifier: Operating System :: OS Independent
Requires-Python: >=3.0
Requires-Dist: numpy
Requires-Dist: pandas
Requires-Dist: tushare
Requires-Dist: pandas-datareader
